{
  "name": "Adventure",
  "url": "https://anilist.co/forum/thread/6111/comment/675370",
  "badge": [
    {
      "name": "Easy Mode",
      "image": "https://i.postimg.cc/hjCf4qkp/Genre-Adventure-Easy.png",
      "started": "2021-02-20",
      "completed": "2021-12-16",
      "status": "completed"
    },
    {
      "name": "Normal Mode",
      "image":"https://i.postimg.cc/xTNcQht3/Genre-Adventure-Normal.png",
      "started": "2021-02-20",
      "completed": "2023-03-18",
      "status": "completed"
    },
    {
      "name": "Hard Mode",
      "image": "https://i.postimg.cc/RCyZgG46/Genre-Adventure-Hard.png",
      "started": "2021-02-20",
      "status": "in-progress"
    },
    {
      "name": "Mastery",
      "image": "https://i.postimg.cc/vH9rGqgX/AWC-Genre-Adventure-Mastery-Animated.png",
      "status": "hidden"
    }
  ]
}
